changelog.md
tabeltekstilo/__init__.py
tabeltekstilo/__main__.py
tabeltekstilo/cli.py
tabeltekstilo/dictionary.py
tabeltekstilo/index.py
tabeltekstilo/xml.py
tabeltekstilo-1.1.0.dist-info/LICENSES/AGPL-3.0-or-later.txt
tabeltekstilo-1.1.0.dist-info/METADATA
tabeltekstilo-1.1.0.dist-info/WHEEL
tabeltekstilo-1.1.0.dist-info/entry_points.txt
tabeltekstilo-1.1.0.dist-info/RECORD
