Metadata-Version: 2.1
Name: tabeltekstilo
Version: 1.1.0
Summary: multi-purpose tool for manipulating text in tabular data format
License: AGPL-3.0-or-later
Keywords: alphabetical,index,indexer,pandas,spreadsheet,tabular,text,xml
Author: hugues de keyzer
Requires-Python: >=3.9,<4.0
Classifier: License :: OSI Approved :: GNU Affero General Public License v3 or later (AGPLv3+)
Classifier: Programming Language :: Python :: 3
Classifier: Programming Language :: Python :: 3.9
Classifier: Programming Language :: Python :: 3.10
Classifier: Programming Language :: Python :: 3.11
Classifier: Programming Language :: Python :: 3.12
Classifier: Topic :: Text Processing :: General
Classifier: Topic :: Text Processing :: Indexing
Requires-Dist: numpy (==1.24.4)
Requires-Dist: odfpy (==1.4.1)
Requires-Dist: openpyxl (==3.1.2)
Requires-Dist: pandas (==2.0.3)
Requires-Dist: pyuca (==1.2)
